Workbook
Name aport: APP!$D$18:$D$18
Name patrimonio: APP!$D$21:$D$21
Name qtd_anos: APP!$D$19:$D$19
Name Rendimento_Carteira: APP!$D$14:$D$14
Name salario: APP!$D$13:$D$13
Name sugestao_investimento: APP!$D$15:$D$15
Name tx_mensal: APP!$D$20:$D$20

Sheet APP
B12: CONFIGURAÇÕES
B13: Salário | D13: 4200
B14: Rendimento Carteira | D14: 0.006
B15: Sugestão de Investimento(30%) | D15: =D13*30% -> 1260
B17: INVESTIMENTO MENSAL
B18: Qunato investir por mês? | D18: 1260
B19: Por Quanto Anos? | D19: 10
B20: Taxa de Rendimento mensal? | D20: 0.01079
B21: Patrimônio acumulado? | D21: {=FV(tx_mensal,qtd_anos*12,aport*-1)} -> 306538.11
B22: Dividendos mensais? | D22: {=patrimonio*Rendimento_Carteira} -> 1839.2286
B24: Cenários | D24: Dividendo
B25: Quanto em 2 Anos ? | C25: =FV($D$20,$A26*12,$D$18*-1) -> 34306.81 | D25: {=C25*Rendimento_Carteira} -> 205.84086
A26: 2 | B26: Quanto em 5 Anos ? | C26: =FV($D$20,$A27*12,$D$18*-1) -> 105558.91 | D26: =C26*$D$14 -> 633.35347
A27: 5 | B27: Quanto em 10 Anos ? | C27: =FV($D$20,$A28*12,$D$18*-1) -> 306538.11 | D27: =C27*$D$14 -> 1839.2286
A28: 10 | B28: Quanto em 20 Anos ? | C28: =FV($D$20,$A29*12,$D$18*-1) -> 1417750 | D28: =C28*$D$14 -> 8506.4999
A29: 20 | B29: Quanto em 30 Anos ? | C29: =FV($D$20,$A30*12,$D$18*-1) -> 5445933.8 | D29: =C29*$D$14 -> 32675.603
A30: 30
B32: PERFIL | C32: Conservador
B33: VALOR A SER INVESTIDO POR MÊS | C33: {=aport} -> 1260
B35: TIPO DE FII | C35: Percentual Sugerido | D35: Valores
B36: PAPEL | C36: =VLOOKUP($C$32&"-"&B36,Planilha2!$C$2:$F$20,4,FALSE) -> 0.3 | D36: =C36*$C$33 -> 378
B37: TIJOLO | C37: =VLOOKUP($C$32&"-"&B37,Planilha2!$C$2:$F$20,4,FALSE) -> 0.5 | D37: =C37*$C$33 -> 630
B38: HÍBRIDOS | C38: =VLOOKUP($C$32&"-"&B38,Planilha2!$C$2:$F$20,4,FALSE) -> 0.1 | D38: =C38*$C$33 -> 126
B39: FOFs | C39: =VLOOKUP($C$32&"-"&B39,Planilha2!$C$2:$F$20,4,FALSE) -> 0.1 | D39: =C39*$C$33 -> 126
B40: DESENVOLVIMENTO | C40: =VLOOKUP($C$32&"-"&B40,Planilha2!$C$2:$F$20,4,FALSE) -> 0 | D40: =C40*$C$33 -> 0
B41: HOTELARIAS | C41: =VLOOKUP($C$32&"-"&B41,Planilha2!$C$2:$F$20,4,FALSE) -> 0 | D41: =C41*$C$33 -> 0
D42: =SUM(D36:D41) -> 1260

Sheet Planilha2
C2: CHAVE | D2: PERFIL | E2: TIPOS DE FII | F2: %
C3: =D3&"-"&E3 -> Conservador-PAPEL | D3: Conservador | E3: PAPEL | F3: 0.3
C4: =D4&"-"&E4 -> Conservador-TIJOLO | D4: Conservador | E4: TIJOLO | F4: 0.5
C5: =D5&"-"&E5 -> Conservador-HÍBRIDOS | D5: Conservador | E5: HÍBRIDOS | F5: 0.1
C6: =D6&"-"&E6 -> Conservador-FOFs | D6: Conservador | E6: FOFs | F6: 0.1
C7: =D7&"-"&E7 -> Conservador-DESENVOLVIMENTO | D7: Conservador | E7: DESENVOLVIMENTO | F7: 0
C8: =D8&"-"&E8 -> Conservador-HOTELARIAS | D8: Conservador | E8: HOTELARIAS | F8: 0
C9: =D9&"-"&E9 -> Moderado-PAPEL | D9: Moderado | E9: PAPEL | F9: 0.32
C10: =D10&"-"&E10 -> Moderado-TIJOLO | D10: Moderado | E10: TIJOLO | F10: 0.35
C11: =D11&"-"&E11 -> Moderado-HÍBRIDOS | D11: Moderado | E11: HÍBRIDOS | F11: 0.08
C12: =D12&"-"&E12 -> Moderado-FOFs | D12: Moderado | E12: FOFs | F12: 0.05
C13: =D13&"-"&E13 -> Moderado-DESENVOLVIMENTO | D13: Moderado | E13: DESENVOLVIMENTO | F13: 0.1
C14: =D14&"-"&E14 -> Moderado-HOTELARIAS | D14: Moderado | E14: HOTELARIAS | F14: 0.1
... C20: =D20&"-"&E20 -> Agressivo-HOTELARIAS | D20: Agressivo | E20: HOTELARIAS | F20: 0.1
